ErrorLogger/__init__.py
ErrorLogger/logger.py
ErrorLogger-0.3.dist-info/METADATA
ErrorLogger-0.3.dist-info/WHEEL
ErrorLogger-0.3.dist-info/top_level.txt
ErrorLogger-0.3.dist-info/RECORD
