Metadata-Version: 2.1
Name: ErrorLogger
Version: 0.3
Summary: A simple Python library to capture exceptions and error logs
Home-page: https://github.com/yourusername/ErrorLogger
Author: Your Name
Author-email: your.email@example.com
